MANIFEST.in
README.md
setup.py
ibapi/__init__.py
ibapi/account_summary_tags.py
ibapi/client.py
ibapi/comm.py
ibapi/commission_report.py
ibapi/common.py
ibapi/connection.py
ibapi/contract.py
ibapi/decoder.py
ibapi/enum_implem.py
ibapi/errors.py
ibapi/execution.py
ibapi/message.py
ibapi/news.py
ibapi/object_implem.py
ibapi/order.py
ibapi/order_condition.py
ibapi/order_state.py
ibapi/orderdecoder.py
ibapi/reader.py
ibapi/scanner.py
ibapi/server_versions.py
ibapi/softdollartier.py
ibapi/tag_value.py
ibapi/ticktype.py
ibapi/utils.py
ibapi/wrapper.py
ibapi_sa.egg-info/PKG-INFO
ibapi_sa.egg-info/SOURCES.txt
ibapi_sa.egg-info/dependency_links.txt
ibapi_sa.egg-info/top_level.txt
tests/test_account_summary_tags.py
tests/test_comm.py
tests/test_enum_implem.py
tests/test_order_conditions.py
tests/test_utils.py