Metadata-Version: 2.1
Name: ibapi-sa
Version: 10.19.4
Summary: Python IB API
Home-page: https://interactivebrokers.github.io/tws-api
Author: IBG LLC
Author-email: dnastase@interactivebrokers.com
License: IB API Non-Commercial License or the IB API Commercial License
